LICENSE.txt
psycopg2_pgevents/__init__.py
psycopg2_pgevents/debug.py
psycopg2_pgevents/event.py
psycopg2_pgevents/sql.py
psycopg2_pgevents/trigger.py
psycopg2_pgevents-0.2.2.dist-info/LICENSE.txt
psycopg2_pgevents-0.2.2.dist-info/WHEEL
psycopg2_pgevents-0.2.2.dist-info/METADATA
psycopg2_pgevents-0.2.2.dist-info/RECORD
