Metadata-Version: 2.1
Name: psycopg2-pgevents
Version: 0.2.2
Summary: PostGreSQL LISTEN/NOTIFY functionality, via psycopg2
Home-page: https://github.com/shawalli/psycopg2-pgevents
License: MIT
Author: Shawn Wallis
Author-email: shawn.p.wallis@gmail.com
Requires-Python: >=3.7,<4.0
Classifier: Development Status :: 3 - Alpha
Classifier: Environment :: Web Environment
Classifier: Intended Audience :: Developers
Classifier: License :: OSI Approved :: MIT License
Classifier: Operating System :: OS Independent
Classifier: Programming Language :: Python :: 3
Classifier: Programming Language :: Python :: 3.7
Classifier: Programming Language :: Python :: 3.8
Classifier: Programming Language :: Python :: 3.9
Classifier: Topic :: Database
Classifier: Topic :: Software Development :: Libraries :: Python Modules
Classifier: Topic :: Utilities
Requires-Dist: coveralls (>=2.1.1,<3.0.0)
Requires-Dist: psycopg2-binary (>=2.7.5)
Requires-Dist: pytest (>=5.4.3,<6.0.0)
Requires-Dist: pytest-cov (>=2.10.0,<3.0.0)
Project-URL: Repository, https://github.com/shawalli/psycopg2-pgevents
